jbb.py
jbb-0.1.5.dist-info/LICENSE.txt
jbb-0.1.5.dist-info/METADATA
jbb-0.1.5.dist-info/WHEEL
jbb-0.1.5.dist-info/entry_points.txt
jbb-0.1.5.dist-info/top_level.txt
jbb-0.1.5.dist-info/RECORD
