Metadata-Version: 2.2
Name: jbb
Version: 0.1.5
Summary: Download prebuilt libraries from Binary Builder
Author-email: Ganesh Viswanathan <dev@genotrance.com>
Project-URL: Homepage, https://github.com/genotrance/jbb
Project-URL: Repository, https://github.com/genotrance/jbb
Project-URL: Issues, https://github.com/genotrance/jbb/issues
Classifier: Development Status :: 4 - Beta
Classifier: Environment :: Win32 (MS Windows)
Classifier: Environment :: MacOS X
Classifier: Intended Audience :: Developers
Classifier: Intended Audience :: System Administrators
Classifier: License :: OSI Approved :: MIT License
Classifier: Natural Language :: English
Classifier: Operating System :: MacOS :: MacOS X
Classifier: Operating System :: Microsoft :: Windows
Classifier: Operating System :: POSIX :: Linux
Classifier: Programming Language :: Python :: 3.7
Classifier: Programming Language :: Python :: 3.8
Classifier: Programming Language :: Python :: 3.9
Classifier: Programming Language :: Python :: 3.10
Classifier: Programming Language :: Python :: 3.11
Classifier: Programming Language :: Python :: 3.12
Classifier: Programming Language :: Python :: 3.13
Classifier: Topic :: System :: Software Distribution
License-File: LICENSE.txt
